t_lark/__init__.py
t_lark/ast_utils.py
t_lark/common.py
t_lark/exceptions.py
t_lark/grammar.py
t_lark/indenter.py
t_lark/lark.py
t_lark/lexer.py
t_lark/load_grammar.py
t_lark/parse_tree_builder.py
t_lark/parser_frontends.py
t_lark/py.typed
t_lark/reconstruct.py
t_lark/template_mode.py
t_lark/tree.py
t_lark/tree_matcher.py
t_lark/tree_templates.py
t_lark/utils.py
t_lark/visitors.py
t_lark/__pyinstaller/__init__.py
t_lark/__pyinstaller/hook-t_lark.py
t_lark/grammars/__init__.py
t_lark/grammars/common.lark
t_lark/grammars/lark.lark
t_lark/grammars/python.lark
t_lark/grammars/unicode.lark
t_lark/parsers/__init__.py
t_lark/parsers/cyk.py
t_lark/parsers/earley.py
t_lark/parsers/earley_common.py
t_lark/parsers/earley_forest.py
t_lark/parsers/grammar_analysis.py
t_lark/parsers/lalr_analysis.py
t_lark/parsers/lalr_interactive_parser.py
t_lark/parsers/lalr_parser.py
t_lark/parsers/lalr_parser_state.py
t_lark/parsers/xearley.py
t_lark/tools/__init__.py
t_lark/tools/nearley.py
t_lark/tools/serialize.py
t_lark/tools/standalone.py
t_lark-1.4.0.dist-info/licenses/LICENSE
t_lark-1.4.0.dist-info/METADATA
t_lark-1.4.0.dist-info/WHEEL
t_lark-1.4.0.dist-info/entry_points.txt
t_lark-1.4.0.dist-info/top_level.txt
t_lark-1.4.0.dist-info/RECORD
