Metadata-Version: 2.4
Name: t-lark
Version: 1.4.0
Summary: a modern parsing library
Author-email: Erez Shinan <erezshin@gmail.com>
License: MIT
Project-URL: Homepage, https://github.com/habemus-papadum/t-lark
Project-URL: Download, https://github.com/habemus-papadum/t-lark/tarball/master
Keywords: Earley,LALR,parser,parsing,ast
Classifier: Development Status :: 5 - Production/Stable
Classifier: Intended Audience :: Developers
Classifier: Programming Language :: Python :: 3
Classifier: Topic :: Software Development :: Libraries :: Python Modules
Classifier: Topic :: Text Processing :: General
Classifier: Topic :: Text Processing :: Linguistic
Classifier: License :: OSI Approved :: MIT License
Requires-Python: >=3.14
License-File: LICENSE
Provides-Extra: regex
Requires-Dist: regex; extra == "regex"
Provides-Extra: nearley
Requires-Dist: js2py; extra == "nearley"
Provides-Extra: atomic-cache
Requires-Dist: atomicwrites; extra == "atomic-cache"
Provides-Extra: interegular
Requires-Dist: interegular<0.4.0,>=0.3.1; extra == "interegular"
Dynamic: license-file
